{
  "chamber": "senate",
  "committee": "Intelligence",
  "baseUrl": "http://www.intelligence.senate.gov",
  "meta": [],
  "sessions": [
    110,
    111,
    112,
    113
  ],
  "hearings": [
    {
      "url": "http://www.intelligence.senate.gov/hearings.cfm?hearingId=e655f9e2809e5476862f735da162d966",
      "date": "2010-09-21T21:30:00.000Z",
      "dateReadable": "September 21st 2010, 2:30 pm",
      "shortdate": "100921",
      "room": "",
      "session": 111,
      "description": "Open Hearing: Nomination of David Buckley to be Inspector General of the Central Intelligence Agency",
      "witnesses": [],
      "links": [
        {
          "url": "http://www.intelligence.senate.gov/hearings.cfm?hearingid=e655f9e2809e5476862f735da162d966&witnessId=e655f9e2809e5476862f735da162d966-0-4",
          "description": ""
        },
        {
          "url": "http://www.intelligence.senate.gov/hearings.cfm?hearingid=e655f9e2809e5476862f735da162d966&witnessId=e655f9e2809e5476862f735da162d966-0-5",
          "description": ""
        },
        {
          "url": "undefined//hearings.cfm?hearingid=e655f9e2809e5476862f735da162d966&witnessId=e655f9e2809e5476862f735da162d966-0-4",
          "description": ""
        },
        {
          "url": "undefined//hearings.cfm?hearingid=e655f9e2809e5476862f735da162d966&witnessId=e655f9e2809e5476862f735da162d966-0-5",
          "description": ""
        }
      ],
      "pdfs": [
        {
          "url": "http://intelligence.senate.gov/100921/statement.pdf",
          "description": "Opening Statement"
        },
        {
          "url": "http://intelligence.senate.gov/100921/questionnaire.pdf",
          "description": "Responses to Questionnaire for Completion by Presidential Nominees"
        },
        {
          "url": "http://intelligence.senate.gov/100921/prehearing.pdf",
          "description": "Responses to Additional Prehearing Questions"
        }
      ],
      "videos": [
        {
          "url": "",
          "type": "HDS",
          "description": "Archived Video - RealPlayer is Required",
          "metadata": {}
        },
        {
          "url": "",
          "type": "HDS",
          "description": "Archived Video - RealPlayer is Required",
          "metadata": {}
        }
      ],
      "path": "/var/www/html/hearings/111/100921"
    },
    {
      "url": "http://www.intelligence.senate.gov/hearings.cfm?hearingId=e655f9e2809e5476862f735da1606609",
      "date": "2010-07-20T21:45:00.000Z",
      "dateReadable": "July 20th 2010, 2:45 pm",
      "shortdate": "100720",
      "room": "Dirksen-SDG-50",
      "session": 111,
      "description": "Open Hearing: Nomination of James R. Clapper, Jr., to be Director of National Intelligence",
      "witnesses": [],
      "links": [
        {
          "url": "http://www.intelligence.senate.gov/</a",
          "description": ""
        },
        {
          "url": "http://www.intelligence.senate.gov/hearings.cfm?hearingid=e655f9e2809e5476862f735da1606609&witnessId=e655f9e2809e5476862f735da1606609-0-3",
          "description": ""
        },
        {
          "url": "http://www.intelligence.senate.gov/hearings.cfm?hearingid=e655f9e2809e5476862f735da1606609&witnessId=e655f9e2809e5476862f735da1606609-0-9",
          "description": "Archived Video"
        },
        {
          "url": "undefined/</a",
          "description": ""
        },
        {
          "url": "undefined//hearings.cfm?hearingid=e655f9e2809e5476862f735da1606609&witnessId=e655f9e2809e5476862f735da1606609-0-3",
          "description": ""
        },
        {
          "url": "undefined//hearings.cfm?hearingid=e655f9e2809e5476862f735da1606609&witnessId=e655f9e2809e5476862f735da1606609-0-9",
          "description": "Archived Video"
        }
      ],
      "pdfs": [
        {
          "url": "http://intelligence.senate.gov/100720/clapper.pdf",
          "description": "Opening Statement"
        },
        {
          "url": "http://intelligence.senate.gov/100720/clapperqfrs.pdf",
          "description": "Responses to Questionnaire for Completion by Presidential Nominees"
        },
        {
          "url": "http://intelligence.senate.gov/100720/clapperpre.pdf",
          "description": "Responses to Additional Prehearing Questions"
        },
        {
          "url": "http://intelligence.senate.gov/100720/attach.pdf",
          "description": "Attachments to Responses to Questionnaire for Completion by Presidential Nominees"
        },
        {
          "url": "http://intelligence.senate.gov/100720/clapperpost.pdf",
          "description": "Responses to Post-hearing Questions"
        },
        {
          "url": "http://intelligence.senate.gov/100720/attach2.pdf",
          "description": "Attachments to Responses to Post-Hearing Questions"
        }
      ],
      "videos": [],
      "path": "/var/www/html/hearings/111/100720"
    },
    {
      "url": "http://www.intelligence.senate.gov/hearings.cfm?hearingId=e655f9e2809e5476862f735da1563493",
      "date": "2010-02-02T22:30:00.000Z",
      "dateReadable": "February 2nd 2010, 2:30 pm",
      "shortdate": "100202",
      "room": "Hart-SH-216",
      "session": 111,
      "description": "Open Hearing: Current and Projected Threats to the United States",
      "witnesses": [
        {
          "name": "The Honorable Dennis C. Blair",
          "title": "",
          "url": "http://www.intelligence.senate.gov/hearings.cfm?hearingid=e655f9e2809e5476862f735da1563493&witnessId=e655f9e2809e5476862f735da1563493-0-1",
          "witnessId": "e655f9e2809e5476862f735da1563493-0-1"
        }
      ],
      "links": [
        {
          "url": "http://www.intelligence.senate.gov/hearings.cfm?hearingid=e655f9e2809e5476862f735da1563493&witnessId=e655f9e2809e5476862f735da1563493-0-2",
          "description": "Archived Video"
        },
        {
          "url": "http://www.intelligence.senate.gov/hearings.cfm?hearingid=e655f9e2809e5476862f735da1563493&witnessId=e655f9e2809e5476862f735da1563493-0-3",
          "description": "Archived Video"
        },
        {
          "url": "undefined//hearings.cfm?hearingid=e655f9e2809e5476862f735da1563493&witnessId=e655f9e2809e5476862f735da1563493-0-2",
          "description": "Archived Video"
        },
        {
          "url": "undefined//hearings.cfm?hearingid=e655f9e2809e5476862f735da1563493&witnessId=e655f9e2809e5476862f735da1563493-0-3",
          "description": "Archived Video"
        }
      ],
      "pdfs": [],
      "videos": [],
      "path": "/var/www/html/hearings/111/100202"
    },
    {
      "url": "http://www.intelligence.senate.gov/hearings.cfm?hearingId=e655f9e2809e5476862f735da153e181",
      "date": "2009-12-01T22:30:00.000Z",
      "dateReadable": "December 1st 2009, 2:30 pm",
      "shortdate": "091201",
      "room": "",
      "session": 111,
      "description": "Open Hearing: Nomination of Philip S. Goldberg to be Assistant Secretary of State for Intelligence and Research and Caryn A. Wagner to be Under Secretary for Intelligence and Analysis, Department of Homeland Security",
      "witnesses": [
        {
          "name": "Philip S. Goldberg",
          "title": "",
          "url": "http://www.intelligence.senate.gov/hearings.cfm?hearingid=e655f9e2809e5476862f735da153e181&witnessId=e655f9e2809e5476862f735da153e181-0-1",
          "witnessId": "e655f9e2809e5476862f735da153e181-0-1"
        }
      ],
      "links": [
        {
          "url": "http://www.intelligence.senate.gov/hearings.cfm?hearingid=e655f9e2809e5476862f735da153e181&witnessId=e655f9e2809e5476862f735da153e181-0-2",
          "description": "Opening Statement"
        },
        {
          "url": "http://www.intelligence.senate.gov/hearings.cfm?hearingid=e655f9e2809e5476862f735da153e181&witnessId=e655f9e2809e5476862f735da153e181-0-3",
          "description": "Responses to Additional Prehearing Questions"
        },
        {
          "url": "http://www.intelligence.senate.gov/hearings.cfm?hearingid=e655f9e2809e5476862f735da153e181&witnessId=e655f9e2809e5476862f735da153e181-0-4",
          "description": "Opening Statement"
        },
        {
          "url": "http://www.intelligence.senate.gov/hearings.cfm?hearingid=e655f9e2809e5476862f735da153e181&witnessId=e655f9e2809e5476862f735da153e181-0-5",
          "description": "Responses to Questionnaire for Completion by Presidential Nominees"
        },
        {
          "url": "http://www.intelligence.senate.gov/hearings.cfm?hearingid=e655f9e2809e5476862f735da153e181&witnessId=e655f9e2809e5476862f735da153e181-0-6",
          "description": "Responses to Additional Prehearing Questions"
        },
        {
          "url": "http://www.intelligence.senate.gov/hearings.cfm?hearingid=e655f9e2809e5476862f735da153e181&witnessId=e655f9e2809e5476862f735da153e181-0-7",
          "description": "Responses to Questionnaire for Completion by Presidential Nominees"
        },
        {
          "url": "http://www.intelligence.senate.gov/hearings.cfm?hearingid=e655f9e2809e5476862f735da153e181&witnessId=e655f9e2809e5476862f735da153e181-0-8",
          "description": "Archived Video"
        },
        {
          "url": "http://www.intelligence.senate.gov/hearings.cfm?hearingid=e655f9e2809e5476862f735da153e181&witnessId=e655f9e2809e5476862f735da153e181-0-9",
          "description": "Responses to Post-hearing Questions"
        },
        {
          "url": "http://www.intelligence.senate.gov/hearings.cfm?hearingid=e655f9e2809e5476862f735da153e181&witnessId=e655f9e2809e5476862f735da153e181-0-10",
          "description": "Responses to Post-hearing Questions"
        },
        {
          "url": "undefined//hearings.cfm?hearingid=e655f9e2809e5476862f735da153e181&witnessId=e655f9e2809e5476862f735da153e181-0-2",
          "description": "Opening Statement"
        },
        {
          "url": "undefined//hearings.cfm?hearingid=e655f9e2809e5476862f735da153e181&witnessId=e655f9e2809e5476862f735da153e181-0-3",
          "description": "Responses to Additional Prehearing Questions"
        },
        {
          "url": "undefined//hearings.cfm?hearingid=e655f9e2809e5476862f735da153e181&witnessId=e655f9e2809e5476862f735da153e181-0-4",
          "description": "Opening Statement"
        },
        {
          "url": "undefined//hearings.cfm?hearingid=e655f9e2809e5476862f735da153e181&witnessId=e655f9e2809e5476862f735da153e181-0-5",
          "description": "Responses to Questionnaire for Completion by Presidential Nominees"
        },
        {
          "url": "undefined//hearings.cfm?hearingid=e655f9e2809e5476862f735da153e181&witnessId=e655f9e2809e5476862f735da153e181-0-6",
          "description": "Responses to Additional Prehearing Questions"
        },
        {
          "url": "undefined//hearings.cfm?hearingid=e655f9e2809e5476862f735da153e181&witnessId=e655f9e2809e5476862f735da153e181-0-7",
          "description": "Responses to Questionnaire for Completion by Presidential Nominees"
        },
        {
          "url": "undefined//hearings.cfm?hearingid=e655f9e2809e5476862f735da153e181&witnessId=e655f9e2809e5476862f735da153e181-0-8",
          "description": "Archived Video"
        },
        {
          "url": "undefined//hearings.cfm?hearingid=e655f9e2809e5476862f735da153e181&witnessId=e655f9e2809e5476862f735da153e181-0-9",
          "description": "Responses to Post-hearing Questions"
        },
        {
          "url": "undefined//hearings.cfm?hearingid=e655f9e2809e5476862f735da153e181&witnessId=e655f9e2809e5476862f735da153e181-0-10",
          "description": "Responses to Post-hearing Questions"
        }
      ],
      "pdfs": [],
      "videos": [],
      "path": "/var/www/html/hearings/111/091201"
    },
    {
      "url": "http://www.intelligence.senate.gov/hearings.cfm?hearingId=e655f9e2809e5476862f735da1515315",
      "date": "2009-10-13T21:30:00.000Z",
      "dateReadable": "October 13th 2009, 2:30 pm",
      "shortdate": "091013",
      "room": "Dirksen-SD-106",
      "session": 111,
      "description": "Open Hearing: Nomination of David Gompert to be Principal Deputy Director of National Intelligence",
      "witnesses": [],
      "links": [
        {
          "url": "http://www.intelligence.senate.gov/hearings.cfm?hearingid=e655f9e2809e5476862f735da1515315&witnessId=e655f9e2809e5476862f735da1515315-0-3",
          "description": ""
        },
        {
          "url": "http://www.intelligence.senate.gov/hearings.cfm?hearingid=e655f9e2809e5476862f735da1515315&witnessId=e655f9e2809e5476862f735da1515315-0-10",
          "description": "Archived Video"
        },
        {
          "url": "http://www.intelligence.senate.gov/hearings.cfm?hearingid=e655f9e2809e5476862f735da1515315&witnessId=e655f9e2809e5476862f735da1515315-0-11",
          "description": "Archived Video"
        },
        {
          "url": "http://www.intelligence.senate.gov/hearings.cfm?hearingid=e655f9e2809e5476862f735da1515315&witnessId=e655f9e2809e5476862f735da1515315-0-0",
          "description": "Archived Video"
        },
        {
          "url": "undefined//hearings.cfm?hearingid=e655f9e2809e5476862f735da1515315&witnessId=e655f9e2809e5476862f735da1515315-0-3",
          "description": ""
        },
        {
          "url": "undefined//hearings.cfm?hearingid=e655f9e2809e5476862f735da1515315&witnessId=e655f9e2809e5476862f735da1515315-0-10",
          "description": "Archived Video"
        },
        {
          "url": "undefined//hearings.cfm?hearingid=e655f9e2809e5476862f735da1515315&witnessId=e655f9e2809e5476862f735da1515315-0-11",
          "description": "Archived Video"
        },
        {
          "url": "undefined//hearings.cfm?hearingid=e655f9e2809e5476862f735da1515315&witnessId=e655f9e2809e5476862f735da1515315-0-0",
          "description": "Archived Video"
        }
      ],
      "pdfs": [
        {
          "url": "http://intelligence.senate.gov/091013/statement.pdf",
          "description": "Opening Statement"
        },
        {
          "url": "http://intelligence.senate.gov/091013/gompert1.pdf",
          "description": "Responses to Questionnaire for Completion by Presidential Nominees"
        },
        {
          "url": "http://intelligence.senate.gov/091013/gompert2.pdf",
          "description": "Responses to Additional Prehearing Questions"
        },
        {
          "url": "http://intelligence.senate.gov/091013/postqfrs.pdf",
          "description": "Responses to Post-hearing Questions"
        },
        {
          "url": "http://intelligence.senate.gov/091013/gompert3.pdf",
          "description": "Confirmation by Senate"
        }
      ],
      "videos": [],
      "path": "/var/www/html/hearings/111/091013"
    },
    {
      "url": "http://www.intelligence.senate.gov/hearings.cfm?hearingId=e655f9e2809e5476862f735da149db56",
      "date": "2009-05-21T21:30:00.000Z",
      "dateReadable": "May 21st 2009, 2:30 pm",
      "shortdate": "090521",
      "room": "Hart-216",
      "session": 111,
      "description": "Open Hearing: Nomination of Stephen W. Preston to be General Counsel of the Central Intelligence Agency and Robert S. Litt to be General Counsel of the Office of the Director of National Intelligence",
      "witnesses": [
        {
          "name": "Robert S. Litt",
          "title": "",
          "url": "http://www.intelligence.senate.gov/hearings.cfm?hearingid=e655f9e2809e5476862f735da149db56&witnessId=e655f9e2809e5476862f735da149db56-0-1",
          "witnessId": "e655f9e2809e5476862f735da149db56-0-1"
        },
        {
          "name": "Stephen W. Preston",
          "title": "",
          "url": "http://www.intelligence.senate.gov/hearings.cfm?hearingid=e655f9e2809e5476862f735da149db56&witnessId=e655f9e2809e5476862f735da149db56-0-4",
          "witnessId": "e655f9e2809e5476862f735da149db56-0-4"
        }
      ],
      "links": [
        {
          "url": "http://www.intelligence.senate.gov/hearings.cfm?hearingid=e655f9e2809e5476862f735da149db56&witnessId=e655f9e2809e5476862f735da149db56-0-3",
          "description": ""
        },
        {
          "url": "http://www.intelligence.senate.gov/hearings.cfm?hearingid=e655f9e2809e5476862f735da149db56&witnessId=e655f9e2809e5476862f735da149db56-0-6",
          "description": ""
        },
        {
          "url": "http://www.intelligence.senate.gov/hearings.cfm?hearingid=e655f9e2809e5476862f735da149db56&witnessId=e655f9e2809e5476862f735da149db56-0-11",
          "description": "Archived Video"
        },
        {
          "url": "undefined//hearings.cfm?hearingid=e655f9e2809e5476862f735da149db56&witnessId=e655f9e2809e5476862f735da149db56-0-3",
          "description": ""
        },
        {
          "url": "undefined//hearings.cfm?hearingid=e655f9e2809e5476862f735da149db56&witnessId=e655f9e2809e5476862f735da149db56-0-6",
          "description": ""
        },
        {
          "url": "undefined//hearings.cfm?hearingid=e655f9e2809e5476862f735da149db56&witnessId=e655f9e2809e5476862f735da149db56-0-11",
          "description": "Archived Video"
        }
      ],
      "pdfs": [
        {
          "url": "http://intelligence.senate.gov/090521/littresponses.pdf",
          "description": "Responses to Questionnaire for Completion by Presidential Nominees"
        },
        {
          "url": "http://intelligence.senate.gov/090521/littquestions.pdf",
          "description": "Responses to Additional Prehearing Questions"
        },
        {
          "url": "http://intelligence.senate.gov/090521/prestonquestions.pdf",
          "description": "Responses to Questionnaire for Completion by Presidential Nominees"
        },
        {
          "url": "http://intelligence.senate.gov/090521/prestonresponses.pdf",
          "description": "Responses to Additional Prehearing Questions"
        },
        {
          "url": "http://intelligence.senate.gov/090521/prestonwritings.pdf",
          "description": "Published Writings Submitted to the Committee"
        },
        {
          "url": "http://intelligence.senate.gov/090521/litt.pdf",
          "description": "Opening Statement"
        },
        {
          "url": "http://intelligence.senate.gov/090521/preston.pdf",
          "description": "Opening Statement"
        },
        {
          "url": "http://intelligence.senate.gov/090521/littpostqfrs.pdf",
          "description": "Responses to Post-hearing Questions"
        },
        {
          "url": "http://intelligence.senate.gov/090521/prestonpostqfrs.pdf",
          "description": "Responses to Post-hearing Questions"
        }
      ],
      "videos": [],
      "path": "/var/www/html/hearings/111/090521"
    },
    {
      "url": "http://www.intelligence.senate.gov/hearings.cfm?hearingId=e655f9e2809e5476862f735da144f44b",
      "date": "2009-03-10T21:30:00.000Z",
      "dateReadable": "March 10th 2009, 2:30 pm",
      "shortdate": "090310",
      "room": "Dirksen-SD-106",
      "session": 111,
      "description": "Open Hearing: Nomination of David S. Kris to be Assistant Attorney General for National Security",
      "witnesses": [
        {
          "name": "David S. Kris",
          "title": "",
          "url": "http://www.intelligence.senate.gov/hearings.cfm?hearingid=e655f9e2809e5476862f735da144f44b&witnessId=e655f9e2809e5476862f735da144f44b-0-1",
          "witnessId": "e655f9e2809e5476862f735da144f44b-0-1"
        }
      ],
      "links": [
        {
          "url": "http://www.intelligence.senate.gov/hearings.cfm?hearingid=e655f9e2809e5476862f735da144f44b&witnessId=e655f9e2809e5476862f735da144f44b-0-3",
          "description": "Archived Video"
        },
        {
          "url": "undefined//hearings.cfm?hearingid=e655f9e2809e5476862f735da144f44b&witnessId=e655f9e2809e5476862f735da144f44b-0-3",
          "description": "Archived Video"
        }
      ],
      "pdfs": [
        {
          "url": "http://intelligence.senate.gov/090310/responses.pdf",
          "description": "Responses of David S. Kris to Prehearing Questions"
        }
      ],
      "videos": [],
      "path": "/var/www/html/hearings/111/090310"
    },
    {
      "url": "http://www.intelligence.senate.gov/hearings.cfm?hearingId=e655f9e2809e5476862f735da143b27e",
      "date": "2009-02-12T22:30:00.000Z",
      "dateReadable": "February 12th 2009, 2:30 pm",
      "shortdate": "090212",
      "room": "Hart-216",
      "session": 111,
      "description": "Open Hearing: Current and Projected National Security Threats to the United States",
      "witnesses": [
        {
          "name": "Admiral Dennis C. Blair",
          "title": "",
          "url": "http://www.intelligence.senate.gov/hearings.cfm?hearingid=e655f9e2809e5476862f735da143b27e&witnessId=e655f9e2809e5476862f735da143b27e-0-1",
          "witnessId": "e655f9e2809e5476862f735da143b27e-0-1"
        }
      ],
      "links": [
        {
          "url": "http://www.intelligence.senate.gov/hearings.cfm?hearingid=e655f9e2809e5476862f735da143b27e&witnessId=e655f9e2809e5476862f735da143b27e-0-2",
          "description": "Archived Video"
        },
        {
          "url": "undefined//hearings.cfm?hearingid=e655f9e2809e5476862f735da143b27e&witnessId=e655f9e2809e5476862f735da143b27e-0-2",
          "description": "Archived Video"
        }
      ],
      "pdfs": [],
      "videos": [],
      "path": "/var/www/html/hearings/111/090212"
    },
    {
      "url": "http://www.intelligence.senate.gov/hearings.cfm?hearingId=e655f9e2809e5476862f735da143525e",
      "date": "2009-02-06T18:00:00.000Z",
      "dateReadable": "February 6th 2009, 10:00 am",
      "shortdate": "090206",
      "room": "Hart-216",
      "session": 111,
      "description": "Open Hearing: Nomination of Leon Panetta to be Director of Central Intelligence Agency",
      "witnesses": [],
      "links": [
        {
          "url": "http://intelligence.senate.gov/hearings.cfm?hearingId=3648",
          "description": "Nomination of Leon Panetta to be Director of Central Intelligence Agency, February 5, 2009"
        },
        {
          "url": "http://www.intelligence.senate.gov/hearings.cfm?hearingid=e655f9e2809e5476862f735da143525e&witnessId=e655f9e2809e5476862f735da143525e-0-2",
          "description": "Archived Video"
        },
        {
          "url": "undefined//hearings.cfm?hearingid=e655f9e2809e5476862f735da143525e&witnessId=e655f9e2809e5476862f735da143525e-0-2",
          "description": "Archived Video"
        }
      ],
      "pdfs": [],
      "videos": [],
      "path": "/var/www/html/hearings/111/090206"
    },
    {
      "url": "http://www.intelligence.senate.gov/hearings.cfm?hearingId=e655f9e2809e5476862f735da1432d86",
      "date": "2009-02-05T22:30:00.000Z",
      "dateReadable": "February 5th 2009, 2:30 pm",
      "shortdate": "090205",
      "room": "Dirksen-G-50",
      "session": 111,
      "description": "Open Hearing: Nomination of Leon Panetta to be Director of Central Intelligence Agency",
      "witnesses": [],
      "links": [
        {
          "url": "http://www.intelligence.senate.gov/hearings.cfm?hearingid=e655f9e2809e5476862f735da1432d86&witnessId=e655f9e2809e5476862f735da1432d86-0-5",
          "description": "Archived Video"
        },
        {
          "url": "undefined//hearings.cfm?hearingid=e655f9e2809e5476862f735da1432d86&witnessId=e655f9e2809e5476862f735da1432d86-0-5",
          "description": "Archived Video"
        }
      ],
      "pdfs": [
        {
          "url": "http://intelligence.senate.gov/090205/answers.pdf",
          "description": "Panetta Responses to Pre-hearing Questions"
        },
        {
          "url": "http://intelligence.senate.gov/090205/panetta_bond.pdf",
          "description": "Panetta Responses to Vice Chairman Bond Questions"
        },
        {
          "url": "http://intelligence.senate.gov/090205/panetta.pdf",
          "description": "Statement of Leon Panetta"
        },
        {
          "url": "http://intelligence.senate.gov/090205/panetta_post.pdf",
          "description": "Panetta Responses to Post-hearing Questions"
        }
      ],
      "videos": [],
      "path": "/var/www/html/hearings/111/090205"
    },
    {
      "url": "http://www.intelligence.senate.gov/hearings.cfm?hearingId=e655f9e2809e5476862f735da142dbbc",
      "date": "2009-01-22T18:00:00.000Z",
      "dateReadable": "January 22nd 2009, 10:00 am",
      "shortdate": "090122",
      "room": "Hart-216",
      "session": 111,
      "description": "Open Hearing: Nomination of Admiral Dennis Blair to be Director of National Intelligence",
      "witnesses": [
        {
          "name": "Admiral Dennis C. Blair",
          "title": "",
          "url": "http://www.intelligence.senate.gov/hearings.cfm?hearingid=e655f9e2809e5476862f735da142dbbc&witnessId=e655f9e2809e5476862f735da142dbbc-0-1",
          "witnessId": "e655f9e2809e5476862f735da142dbbc-0-1"
        }
      ],
      "links": [
        {
          "url": "http://www.intelligence.senate.gov/hearings.cfm?hearingid=e655f9e2809e5476862f735da142dbbc&witnessId=e655f9e2809e5476862f735da142dbbc-0-4",
          "description": "Archived Video"
        },
        {
          "url": "http://www.intelligence.senate.gov/hearings.cfm?hearingid=e655f9e2809e5476862f735da142dbbc&witnessId=e655f9e2809e5476862f735da142dbbc-0-5",
          "description": "Archived Video"
        },
        {
          "url": "undefined//hearings.cfm?hearingid=e655f9e2809e5476862f735da142dbbc&witnessId=e655f9e2809e5476862f735da142dbbc-0-4",
          "description": "Archived Video"
        },
        {
          "url": "undefined//hearings.cfm?hearingid=e655f9e2809e5476862f735da142dbbc&witnessId=e655f9e2809e5476862f735da142dbbc-0-5",
          "description": "Archived Video"
        }
      ],
      "pdfs": [
        {
          "url": "http://www.intelligence.senate.gov/090122/blairresponses.pdf",
          "description": "Responses of Dennis C. Blair to Prehearing Questions"
        },
        {
          "url": "http://www.intelligence.senate.gov/090122/blairresponses2.pdf",
          "description": "Responses to Dennis C. Blair Post-hearing Questions"
        },
        {
          "url": "undefined/090122/blairresponses.pdf",
          "description": "Responses of Dennis C. Blair to Prehearing Questions"
        },
        {
          "url": "undefined/090122/blairresponses2.pdf",
          "description": "Responses to Dennis C. Blair Post-hearing Questions"
        }
      ],
      "videos": [],
      "path": "/var/www/html/hearings/111/090122"
    }
  ]
}